kickpy/__init__.py
kickpy/client.py
kickpy/errors.py
kickpy/utils.py
kickpy/models/__init__.py
kickpy/models/access_token.py
kickpy/models/categories.py
kickpy/models/channel.py
kickpy/models/events_subscriptions.py
kickpy/models/livestreams.py
kickpy/models/stream.py
kickpy/models/user.py
kickpy/models/webhooks/__init__.py
kickpy/models/webhooks/_shared.py
kickpy/models/webhooks/channel_follow.py
kickpy/models/webhooks/channel_sub_created.py
kickpy/models/webhooks/channel_sub_gifts.py
kickpy/models/webhooks/channel_sub_renewal.py
kickpy/models/webhooks/chat_message.py
kickpy/models/webhooks/kicks_gifted.py
kickpy/models/webhooks/livestream_metadata.py
kickpy/models/webhooks/livestream_status.py
kickpy/models/webhooks/moderation_banned.py
kickpy/webhooks/__init__.py
kickpy/webhooks/enums.py
kickpy/webhooks/server.py
kickcom_py-0.1.2.dist-info/licenses/LICENSE
kickcom_py-0.1.2.dist-info/WHEEL
kickcom_py-0.1.2.dist-info/METADATA
kickcom_py-0.1.2.dist-info/RECORD
