Metadata-Version: 2.4
Name: kickcom.py
Version: 0.1.2
Summary: Async library for Kick.com API and webhooks
Author: PredaaA
Requires-Python: >=3.8
Classifier: Development Status :: 3 - Alpha
Classifier: Intended Audience :: Developers
Classifier: License :: OSI Approved :: MIT License
Classifier: Operating System :: OS Independent
Classifier: Programming Language :: Python :: 3 :: Only
Classifier: Programming Language :: Python :: 3.9
Classifier: Programming Language :: Python :: 3.10
Classifier: Programming Language :: Python :: 3.11
Classifier: Programming Language :: Python :: 3.12
Classifier: Programming Language :: Python :: 3.13
Classifier: Programming Language :: Python :: 3.14
License-File: LICENSE
Requires-Dist: aiohttp>=3.11.14
Requires-Dist: cryptography>=44.0.2
Requires-Dist: orjson>=3.10.16 ; extra == "speed"
Requires-Dist: aiodns>=1.1 ; extra == "speed" and ( sys_platform != 'win32')
Requires-Dist: Brotli ; extra == "speed"
Requires-Dist: cchardet==2.1.7 ; extra == "speed" and ( python_version < '3.10')
Project-URL: Home, https://github.com/PredaaA/kickcom.py
Project-URL: Issue Tracker, https://github.com/PredaaA/kickcom.py/issues
Project-URL: Source Code, https://github.com/PredaaA/kickcom.py
Provides-Extra: speed
